{
    "companyInfo": {
      "companyName": "O'conner - Lakin",
      "companyMotto": "cutting-edge integrate relationships",
      "companyEst": "2023-05-26T05:03:01.855Z"
    },
    "employees": [
      {
        "id": "d3be8f87-a631-41ca-a344-852c650cf608",
        "avatar": "https://s3.amazonaws.com/uifaces/faces/twitter/mtolokonnikov/128.jpg",
        "firstName": "Alexis",
        "lastName": "Ross",
        "jobTitle": "Investor Implementation Officer",
        "contactNo": "0462 594 839",
        "address": "Casper Boulevard Murraymouth, Australian Capital Territory",
        "age": 63,
        "bio": "Repellat beatae voluptatem quam facilis qui. Alias eos facilis dolorem id. Eaque vel similique cum libero. Ea necessitatibus necessitatibus voluptas ea. Inventore vitae maxime. Non velit nam dicta molestiae quas.",
        "dateJoined": "2023-04-13T10:53:46.566Z"
      },
      {
        "id": "e0478e9c-d3d6-4e40-a615-14ecc595d7e3",
        "avatar": "https://s3.amazonaws.com/uifaces/faces/twitter/katiemdaly/128.jpg",
        "firstName": "Savannah",
        "lastName": "Weber",
        "jobTitle": "Dynamic Creative Engineer",
        "contactNo": "0444 061 819",
        "address": "Thomson Street Scottland, Victoria",
        "age": 47,
        "bio": "Cum omnis nam et temporibus dignissimos est nam. Nam et iste labore corrupti consequatur perferendis. Cumque doloribus et et fuga iste error. Sunt dolor consequuntur consequatur.",
        "dateJoined": "2021-09-01T19:16:19.036Z"
      },
      {
        "id": "c97982b7-e52b-470a-9cbf-2dcb9235ac3d",
        "avatar": "https://s3.amazonaws.com/uifaces/faces/twitter/ratbus/128.jpg",
        "firstName": "Zachary",
        "lastName": "Murphy",
        "jobTitle": "Dynamic Web Facilitator",
        "contactNo": "0492 277 965",
        "address": "Collins View Rd Koelpinchester, Queensland",
        "age": 59,
        "bio": "Non excepturi aut qui non necessitatibus aliquid consectetur. Ipsum molestiae beatae animi quo dolorum molestias dolorem rerum. Et voluptatibus provident quae. Fugiat quo officia culpa doloremque. Sunt possimus ex omnis.",
        "dateJoined": "2016-03-19T04:08:44.602Z"
      },
      {
        "id": "e97a4a77-8728-4f75-b658-2fad0a9f29eb",
        "avatar": "https://s3.amazonaws.com/uifaces/faces/twitter/lhausermann/128.jpg",
        "firstName": "Ali",
        "lastName": "Marvin",
        "jobTitle": "Future Directives Planner",
        "contactNo": "0466 502 793",
        "address": "Victoria Boulevard O'keefeland, Australian Capital Territory",
        "age": 47,
        "bio": "Et tempore odit perferendis. Ab consequatur autem numquam. Exercitationem voluptate magni consequuntur. Rerum veritatis earum ipsa facilis nam. Enim ut quos quas repellat commodi suscipit sunt dolorem. Et totam tenetur possimus.",
        "dateJoined": "2019-12-20T23:46:06.227Z"
      },
      {
        "id": "fc593c9a-0d23-4919-8aef-406ab9545d7e",
        "avatar": "https://s3.amazonaws.com/uifaces/faces/twitter/kojourin/128.jpg",
        "firstName": "Justin",
        "lastName": "Stark",
        "jobTitle": "Legacy Accountability Agent",
        "contactNo": "0426 108 791",
        "address": "Holly Way Thomasmouth, Northern Territory",
        "age": 59,
        "bio": "Eveniet ex iure vitae nihil. Minima deleniti blanditiis molestias voluptatum iste aliquam nostrum dicta eum. Aliquid vel non voluptas in qui molestiae dolorum molestiae exercitationem. Vel reprehenderit maiores vel illo quia non enim.",
        "dateJoined": "2022-10-13T22:00:04.233Z"
      },
      {
        "id": "4c78b6d4-0885-45bf-b274-cfad7d89826f",
        "avatar": "https://s3.amazonaws.com/uifaces/faces/twitter/netonet_il/128.jpg",
        "firstName": "Hannah",
        "lastName": "Gibson",
        "jobTitle": "Forward Interactions Administrator",
        "contactNo": "0411 547 127",
        "address": "Tyler Track South Davidbury, Tasmania",
        "age": 31,
        "bio": "Voluptates officiis temporibus tenetur vel omnis. Et exercitationem qui in voluptates. Sint modi consequatur voluptatum. Neque consequatur officia. Dolor laudantium eaque consequuntur. Ipsum ab ut accusamus natus eos assumenda unde harum fuga.",
        "dateJoined": "2023-04-16T08:03:38.223Z"
      },
      {
        "id": "e7df3d35-0cbe-4fbb-9590-9a1f7a28793d",
        "avatar": "https://s3.amazonaws.com/uifaces/faces/twitter/betraydan/128.jpg",
        "firstName": "Oscar",
        "lastName": "Stewart",
        "jobTitle": "Central Program Specialist",
        "contactNo": "0467 345 759",
        "address": "Layla Mews South Tyler, New South Wales",
        "age": 20,
        "bio": "Fugit nihil molestiae voluptatem fugit quo nam possimus voluptatum. Sit deserunt ut officia eaque hic est nisi molestiae consequatur. Corrupti incidunt velit ducimus placeat harum.",
        "dateJoined": "2024-03-13T10:48:45.524Z"
      },
      {
        "id": "e82465f6-a9e8-4385-b6f4-11a6a38d7adb",
        "avatar": "https://s3.amazonaws.com/uifaces/faces/twitter/angelcreative/128.jpg",
        "firstName": "Darcy",
        "lastName": "Kulas",
        "jobTitle": "Dynamic Marketing Manager",
        "contactNo": "0459 720 774",
        "address": "Green Knoll East Imogen, Australian Capital Territory",
        "age": 17,
        "bio": "Iure dolor aut voluptates ut qui. Et magnam nesciunt dolor aperiam qui. Vero velit consequuntur quis consectetur eligendi numquam autem labore aut. Saepe facere cupiditate. Numquam repellendus aliquam enim.",
        "dateJoined": "2024-08-14T12:22:47.041Z"
      },
      {
        "id": "89f16368-6e2d-4ac3-acb9-3da607ba3ee8",
        "avatar": "https://s3.amazonaws.com/uifaces/faces/twitter/snowwrite/128.jpg",
        "firstName": "Piper",
        "lastName": "Ward",
        "jobTitle": "Central Tactics Consultant",
        "contactNo": "0446 525 979",
        "address": "Emmerich Court Port Charlie, Australian Capital Territory",
        "age": 53,
        "bio": "Quia laborum vero vero neque nam vel voluptatum. Tempore natus voluptatem sunt et totam. Dolorem quo eveniet dignissimos quidem et omnis voluptates deserunt expedita.",
        "dateJoined": "2022-05-06T20:57:02.466Z"
      },
      {
        "id": "39dab6a8-fa5f-441c-bada-96fd1ebfd8ea",
        "avatar": "https://s3.amazonaws.com/uifaces/faces/twitter/ademilter/128.jpg",
        "firstName": "Max",
        "lastName": "Reid",
        "jobTitle": "Human Integration Representative",
        "contactNo": "0482 786 956",
        "address": "Ivy Knoll Gibsonchester, Queensland",
        "age": 32,
        "bio": "Atque eum quia rerum eum incidunt suscipit explicabo et. Doloremque laudantium iure qui et asperiores eius. Voluptatibus voluptatum dolorum voluptas omnis quas delectus consequuntur doloribus. Veritatis velit et occaecati ratione est enim sed perferendis. Ratione ipsum placeat consectetur.",
        "dateJoined": "2019-04-29T16:04:46.028Z"
      },
      {
        "id": "bd06f300-2e9f-47c0-b320-3264d09bc7d4",
        "avatar": "https://s3.amazonaws.com/uifaces/faces/twitter/chrisslowik/128.jpg",
        "firstName": "Poppy",
        "lastName": "Grant",
        "jobTitle": "Dynamic Interactions Coordinator",
        "contactNo": "0460 827 510",
        "address": "Owen Terrace Port Phoebe, South Australia",
        "age": 21,
        "bio": "Sint provident neque quia neque ab natus est maiores voluptas. Vel est minus tempore. Inventore sit necessitatibus voluptatem mollitia omnis repudiandae assumenda soluta. Est quia vero laborum nobis asperiores vitae qui natus dolores. Esse facere tempora accusamus doloribus. Illum magnam enim suscipit.",
        "dateJoined": "2024-02-12T22:28:28.738Z"
      },
      {
        "id": "31098607-a1ba-4d40-b7a9-12429db2e454",
        "avatar": "https://s3.amazonaws.com/uifaces/faces/twitter/haruintesettden/128.jpg",
        "firstName": "Angus",
        "lastName": "Gutmann",
        "jobTitle": "Corporate Factors Liaison",
        "contactNo": "0442 429 330",
        "address": "Hannah Circuit East Summer, Tasmania",
        "age": 18,
        "bio": "Quis quia blanditiis non placeat dicta accusamus. Similique corporis deserunt omnis sint ut. Nostrum repudiandae voluptas alias nesciunt repudiandae totam voluptates ducimus esse.",
        "dateJoined": "2021-05-11T01:28:04.036Z"
      }
    ]
  }